[
	{
		"name": "나박김치",
		"ingredients": "배추잎 10장, 무 1/3개, 통마늘 5개, 당근 1/2개, 쪽파 1움큼 , 홍고추 2개, 고추가루 5스푼, 설탕 3스푼, 생강가루 1/2티스푼, 소금 3.5스푼, 생수 2L ",
		"recipe": [
			"1. 재료:배추잎 10장,무1/3개,통마늘5개,당근1/2개,쪽파한웅큼,홍고추2개     양념재료: 고추가루5스푼,설탕3스푼,생강가루1/2티스푼,소금3스푼반,생수2리터",
			"2. 물3컵을 준비한뒤 고추가루5스푼을 넣어줍니다.",
			"3. 물과 고추가루가 잘섞이도록 풀어주세요.",
			"4. 통마늘5개를 준비한뒤 채썰어서 준비",
			"5. 당근1/2개를 준비해서 얇게 4등분해서 썰어주세요.",
			"6. 쪽파는 한웅큼을 준비해서 10cm정도로 잘라주시는데 쪽파가 없으면 미나리로대체 가능합니다.",
			"7. 무1/3토막을 나박썰어서 준비합니다.",
			"8. 배추잎10장정도도 먹기 좋게 썰어서 준비",
			"9. 홍고추는 어슷썰어준뒤 고추씨를 모두 제거해주세요.",
			"10. 그릇에 면보를 씌운뒤 고추가루물을 부어줍니다.",
			"11. 면보를 꾸욱 짜서 고추가루와 고추가루물을 분리해주세요     여기서 고추가루 물만 사용할거예요^^",
			"12. 고추가루물에 소금3스푼반,생강가루1/2티스푼,설탕3스푼을 넣어서 풀어줍니다.",
			"13. 큼직한 김치통에      무-배추-당근-쪽파-홍고추      순으로 차곡차곡 넣어줍니다.",
			"14. 고추가루물을 부어준뒤 물 2L를 넣어주세요",
			"15. 고추가루물과 물이 잘섞이도록 풀어준뒤 밖에서 3시간 이상 보관해주세요     바로 먹기 위해 조금 익혀주는 과정이예요     3시간이상 밖에서 보관하다가 냉장고에 넣기전 간을 보고      소금이나 설탕으로 부족한 간을 맞추어준뒤 냉장고에 보관후 차갑게 드시면 됩니다.",
			"16. 초간단 나박김치 만드는법이었어요"
		]
	},
	{
		"name": "나박김치",
		"ingredients": "무 1kg, 알배추 1.2kg, ﻿﻿쪽파 120g, 백오이 2개, 홍고추 3개, 청고추 3개, 마늘 50g, 생강 15g, 배 1개 (즙), 물 25컵, 소금 5~6큰술, 설탕 2~3큰술, 물 4컵, 고춧가루 50g",
		"recipe": [
			"1. 무는 껍질 채 깨끗이 씻어 나박 썰고 배추는 나박 썰어서 씻어놓고 오이는 0.4cm 길이로 자르세요~  모두 김치통에 넣고 소금 40g을 넣은 후 까불러 40분 정도 절이세요.",
			"2. 쪽파는 4~5cm로 썰고 마늘과 생강은 슬라이스로 썰고 고추는 어슷썰기 해놓으세요.",
			"3. 40분이 지난 후 쪽파와 고추 등 썰어 놓은 향신채를 김치통에 넣으세요​.",
			"4. 고춧가루 50g을 베주머니에 담아 물 4컵에 주물러서 30분쯤 미리 불려 준비해 주세요.",
			"5. ​배는 강판에 갈아 즙만 사용하세요. 원액기를 사용해도 좋아요.",
			"6. 고춧물과 배즙과 ​국물 재료를 모두 김치통에 넣고 섞어 주세요. 간을 보고서 입맛에 맞게 재료를 가감하세요.  ​물김치 국물간은 처음에는 약간 짭짤한 듯해야 익어서 여러 재료들과 어우러져서 간이 맞습니다~  ​실온에 두었다가 국물이 익은 듯하면 ​냉장고에 보관하세요~",
			"7. 알맞게 익은 나박김치는 전과 떡과도 잘 어울립니다.  맛있게 먹을 식구들 생각에 마음이 흐뭇하네요.",
			"8. 물김치는 여럿이 같이 떠 먹는 것보다 개인 그릇에 담아주면 모양도 예쁘고 위생적입니다~​"
		]
	},
	{
		"name": "나박김치",
		"ingredients": "배추, 무, 배 1/4개 , 통마늘 6~8개, 생강 1톨, 홍고추 1개, 쪽파, 오이 1/3개, 굵은소금 1컵, 고추가루 3큰술, 소금 2큰술, 설탕 1큰술, 매실청 2큰술",
		"recipe": [
			"1. 배추와 무는 나박썰기로 썰어줍니다. 굳이 cm로 말씀드리자면 대략2.5~3cm정도의 크기입니다.",
			"2. 배추와 무를 분리해서 담아 줍니다. 절이는 시간이 다르기 때문에 꼭 분리를 해서 담아주셔야 합니다.",
			"3. 물10컵에 굵은 소금 1컵을 넣고 소금물을 만들어 줍니다.",
			"4. 배추와 무를 각각 소금물에 절입니다.",
			"5. 무를 30분 / 배추는 40분정도 절인후 1~2번정도 헹군 후 물기를 빼줍니다.",
			"6. 배추와 무가 절여지는 동안 함께 넣어줄 재료들을 손질 합니다. 홍고추,오이,배를 썰어 줍니다. (쪽파를 넣어야 하는데 이번에는 생략 했습니당~)",
			"7. 마늘과 생강은 채를 썰어 줍니다. 다져서 넣어도 되지만 이렇게 썰은 후 다시팩에 넣어주면 국물이 깔끔 해집니다.",
			"8. 마늘과 생강 모두 다시팩에 넣어줍니다.",
			"9. 고추가루 3스푼을 넣은 다시팩을 물 4컵에 풀어줍니다.",
			"10. 고추가루 국물에 물10컵,소금 2큰술,설탕 2큰술,매실청 2큰술을 넣어 양념물을 만들어 줍니다.",
			"11. 담을 통에 배추/무를 넣고 홍고추,배,오이와 함께 잘 섞어 줍니다.",
			"12. 잘 섞어 주셨으면 요기에 양념 국물만 넣어주면 완성입니다.!!!",
			"13. 너무나도 간단한 나박김치입니다"
		]
	},
	{
		"name": "나박김치",
		"ingredients": "알배추 400g, 무 1/2개, 쪽파 100g, 마늘 10쪽, 배 1개, 미나리 1줌, 오이 1/2개, 물 4컵, 소금 1/2컵, 끓인 물 9컵, 찬물 9컵, 소금 1/2컵, 설탕 3T, 고춧가루 1/2컵",
		"recipe": [
			"1. 배추,무는 나박썰기하시고,마늘도 저며서 썰어둡니다.",
			"2. 물4컵에 소금 반컵을 풀어 15분간 절여,찬물에 헹궈 물을 빼둡니다.",
			"3. 끓인 물9컵,찬물9컵을 섞은 물에 소금 반컵,설탕3T,생강가루 1/2t를 넣어주세요. 베보자기에 고춧가루 반컵을 넣어 그 물에 조물조물 주물러서 고춧물을 내주시고요.",
			"4. 절여 씻어놓은 배추,무에 쪽파,오이,배,저민 마늘까지 넣고 양념물을 부어주세요."
		]
	}
]