[
	{
		"name": "돼지갈비구이",
		"ingredients": "돼지목심 1kg, 간장 1/2컵, 설탕 1/2컵, 매실청 1/3컵, 다진마늘 큰술, 양파 1/4개 (간거), 물 2컵, 소주 3큰술",
		"recipe": [
			"1. 우선 냄지에 간장 반컵과 설탕 반컵을 넣고",
			"2. 매실청 1/3컵, 물 2컵 넣어 팔팔 끓여준 후 불을 꺼서 완전히 식혀 줍니다.양념이 식는 동안,",
			"3. 돼지목심에 칼집을 사선으로 내어 주세요. 앞뒤면 고루고루~",
			"4. 그리고 아까 끓인 양념이 다식으면, 소주 1큰술, 다진마늘 2큰술과 양파 1/4를 갈아서 넣어주면 양념끝!ㅋ",
			"5. 이제 칼집낸 돼지고기를 넣어 1일 재워주면 끝!",
			"6. 가열된 팬에 앞뒤로 맛있게 구워주세요~ㅎ"
		]
	},
	{
		"name": "돼지갈비구이",
		"ingredients": "돼지갈비 1900g, 양파 1.5개, 돼지갈비소스 (2근용), 생강 1작은술, 간장 4큰술, 매실액 2큰술, 마늘 3큰술, 홍고추 1개, 청양고추 1개, 월계수잎 3장, 대파 2큰술, 참기름 1큰술",
		"recipe": [
			"1. 돼지갈비를 깨끗이 씻어서 한 시간 동안 핏물을 제거하고 다시 깨끗하게 씻어줍니다.~",
			"2. 양파, 생강,마늘,청양고추, 홍고추, 대파를 준비하고",
			"3. 썰은 야채와 양념소스와 간장 4큰술, 매실액2큰술, 월계수잎 3장 을 잘 섞어 주고요.",
			"4. 양념을 만들어줍니다.",
			"5. 이렇게 갈비랑 잘 버무려 주고",
			"6. 차곡차곡 통에 담아서 하루를 재어서 냉장실에 보관합니다.",
			"7. 갈비를 올리고 지글지글 구우면 되고요.",
			"8. 돼지갈비는 익으면 이렇게 잘 잘라야 한다는 점. 을매나 잘랐는지 모르것네요.^^"
		]
	},
	{
		"name": "돼지갈비구이",
		"ingredients": "돼지고기 목살 1kg, 파인애플 통조림 제일 작은 사이즈 1캔, 양파 중간크기 1개, 진간장 8T, 국간장 2T, 올리고당 3T (or 물엿 꿀), 흑설탕 2T (설탕 대체 무방), 맛술 5T, 다진 마늘 3T, 생강즙 2T, 후추 넉넉히, 대파 다진 것 1대, 청고추 3개, 홍고추 3개, 샐러리 1대, 월계수잎 가루 1T, 고추씨 기름 1T",
		"recipe": [
			"1. 앞뒤로 촘촘하게 칼집을 넣어 주세요. 양념이 쏙쏙 배라고 하는 과정이에요.",
			"2. 파인애플 통조림 제일 작은 사이즈, 링으로 4조각 정도 블렌더로 곱게 갈아 주세요.통조림 안에 들어 있는 국물도 버리지 말고 모두 사용하세요.",
			"3. 양파 중간 사이즈 한개 분량 역시 곱게 갈아 줍니다.",
			"4. 파인애플이랑 양파 갈은 거에요. 고기 냄새 제거, 연육 작용을 하죠~",
			"5. 분량의 양념대로 섞어주시고, 여기서 간을 꼭 봐 주세요~ 짜지 않고 약간 간간한 정도로 살짝 단맛이 도는 상태가 가장 좋아요. 가장 기본이 되는 맛이 여기까지 거든요.",
			"6. 여기에 맛을 더해주는 재료를 넣어 줍니다. 대파 한대 분량 다진 것 + 청홍 고추 각 3개씩 다진 것 간간한 단맛에 시원한 매운맛이 더해져 양념장 맛이 한결 살아날 꺼에요.",
			"7. 생략하셔도 무방하지만 개인적으로 샐러리를 참 좋아하거든요. 씹히는 맛도 좋고 돼지고기 냄새 제거에도 좋고요. 한대 정도 곱게 다져 넣었어요. 역시 생략하셔도 무방한 단계로 월계수잎 가지고 계시면 2~3장 정도 넣어 주셔도 좋아요. 저는 월계수잎 가루를 1T 정도 넣었답니다.",
			"8. 맛을 보시고 약간의 매운맛을 더 원하신다면 고추씨 기름 1T 넣어 주세요.",
			"9. 양념장을 먹어 봐서 짜지 않고 약간 간간한 상태로 살짝 달짝 지근하면서 매콤한 그런 상태가 되면 완성~",
			"10. 칼집 넣은 고기를 넣고 양념이 잘 밸 수 있도록 조물 조물 해 주세요.",
			"11. 차곡 차곡 양념을 부어 가면서 고기를 재웁니다. 이 상태로 대략 하룻밤 정도 두시면 좋아요.",
			"12. 다음날 고기를 구워 먹었죠~~ 양념을 듬뿍 얹어 가면서 구우셔야 해요~"
		]
	},
	{
		"name": "돼지갈비구이",
		"ingredients": "돼지목살 1kg, 진간장 100ml, 설탕 90g, 다진마늘 3큰술, 맛술 5큰술, 배음료 200ml, 양파 1개",
		"recipe": [
			"1. 돼지 목살 1kg을 준비해 주세요.",
			"2. 목살에 칼집을 넣어주시는데 살짝이 아닌 조금은 깊게 넣어주셔야 양념장이 속까지 잘 배서 구웠을 때 정말 맛있는 돼지갈비를 드실 수 있어요. 칼집은 앞 뒷면 모두 넣어주세요.",
			"3. 진간장 100ml, 설탕 90g, 맛술 5스푼, 다진마늘 3스푼을 섞어주세요.",
			"4. 그리고 간양파를 넣어주시는데 간양파는 갈아만든배 200ml에 양파 1개를 조각내 블렌더에 넣고 곱게 갈아 함께 섞어주시면 돼요.",
			"5. 돼지목살을 용기에 담고 갈비양념장을 부어 아래에 깔려 있는 고기를 뒤적여 양념이 잘 밸 수 있도록 해주세요.",
			"6. 달달한 양념장이 잘 밴 고기는 마른 팬에 넣고 소스 3스푼 정도 함께 넣어 중불로 굽기 시작해 주세요.",
			"7. 양념이 바싹 졸아들 때까지 구우면 간이 세질 수 있으니 소스가 자작할 때 마무리 해주세요."
		]
	}
]