[
	{
		"name": "빠르고 쉽게 로즈마리 말려 사용하기-살림의지혜 나누기",
		"ingredients": "로즈마리",
		"recipe": [
			"1. 집게 손가락을 사용하여 줄기를 손가락 끝을 쭈~~~욱 훑어줍니다 그리고 나서 줄기를 던져버리고~~~~~",
			"2. 몇 가지는 뿌리내려 삽목 하려고 유리병에 담아주고",
			"3. 종이 수건 1개를 접시 위에 평평하게 놓아주고",
			"4. 종이타월을 덮어주지 않으면 직접 로즈마리에 전자파가 닿아서 색이 누렇게 변할 수도 있고 좋은 성분이 다 날라갈 것 간다고 하니~",
			"5. 로즈마리를 종이 타월 위에 올려 놓은 다음 위에 또 다른 종이 타월을 얹어서  전자 레인지를 1분간30초간 휘리릭~~~~~",
			"6. 시중에 판매되는 건조 로즈마리보다 색깔이 정말 예쁘게 건조 되었죠?",
			"7. 로즈마리 잎을 흩어내면서 같이 딸려 나온 나뭇가지 부스러기도 정리 할겸 고운 채망에 넣어서 탁탁 털어 줍니다."
		]
	},
	{
		"name": "로즈마리 간장 메로구이",
		"ingredients": "메로몸살 350g, 소금 약간, 후추 약간, 간장 2큰술, 올리고당 1큰술, 포도씨유 1큰술, 레몬즙 1작은술, 다진마늘 1작은술, 로즈마리 약간",
		"recipe": [
			"1. 로즈마리간장소스 재료를 모두 넣고 섞어주시고",
			"2. 메로는 깨끗이 씻어 물기제거후에 소금,후추를 살짝 뿌려주세요",
			"3. 웰빙다용도팬에 유산지를 깔고 로즈마리간장소스를 메로 앞뒤로 발라주신후에",
			"4. 팬에 놓아주신다음 스마트오븐 2단에 놓아주세요. 180도로 15분정도 구워주시면~",
			"5. 샤방샤방 로즈마리간장메로구이 완성입니다."
		]
	},
	{
		"name": "로즈마리 갈릭 항정살 만들기",
		"ingredients": "항정살 300g, 마늘 10알, 로즈마리 3줄기, 식용유 2큰술, 소금 적당량, 후춧가루 적당량",
		"recipe": [
			"1. 깨끗이 씻은 마늘은 반으로 잘라주세요.",
			"2. 항정살을 준비하여 먹기좋은 크기로 썰어주세요,",
			"3. 식용유를 두른 달군 팬에 마늘과 로즈마리를 넣고 마늘이 밝은 갈색이 될 때까지 볶아주세요.",
			"4. 항정살과 소금, 후춧가루를 넣고 항정살이 노릇해질 때까지 볶아 완성한다."
		]
	},
	{
		"name": "로즈마리 로스트 치킨. 에어프라이어로 구웠어요",
		"ingredients": "작은 닭 1마리, 로즈마리 약간, 올리브오일 1큰술, 천일염 넉넉하게, 통후추 적당량",
		"recipe": [
			"1. 깨끗하게 씻은 닭은 군데군데 칼집을 깊숙하게 넣어줍니다.",
			"2. 닭에 전체적으로 천일염을 뿌려주되 칼집부분에 집중적으로 천일염을 뿌려 간을 합니다.",
			"3. 에어프라이어로 굽는 거라 그대로 해도 되지만 겉이 마르는 것을 방지하기 위해 1큰술만 골고루 발라줍니다.",
			"4. 칼집 낸 곳에 로즈마리를 깊숙히 끼워줍니다.",
			"5. 통후추를 넉넉히 갈아서 뿌려줍니다.",
			"6. 에어프라이어에 넣고 180도로 20분 굽고 껍직을 좀 더 바삭하게 하기 위해 200도로 올려 다시 10분간 더 구워줍니다.",
			"7. 완성."
		]
	}
]