[
	{
		"name": "시나몬롤 만들기",
		"ingredients": "밀가루 300g (강력분 혹은 중력분), 드라이이스트 6g, 설탕 30g, 무염버터 40g, 소금 3g, 달걀 1개, 미지근한물 110g, 흑설탕 70g, 시나몬가루 1tsp, 코코아가루 1tsp (혹은 초콜릿가루), 버터 20g, 크림치즈 50g, 버터 40g, 슈가파우더 60g, 바닐라엑스트렉 약간, 소금 1꼬집",
		"recipe": [
			"1. 도우 재료를 다 넣고 반죽을 해줍니다. 이때 이스트와 소금, 설탕은 서로 닿지않게 밀가루로 덮어주시고 반죽 시작해요. 반죽은 스탠드믹서나 반죽기가 있을 경우 5~7분 정도 해주시면 되고 손으로 할 때는 글루텐이 충분히 형성될 수 있게 최소한 10분 이상 해주셔야 해요. 저는 핸드믹서의 도우훅을 이용해 1단으로 돌려줬어요. 반죽은 표면이 매끈해지고 밀가루결이 보일 정도까지 합니다.",
			"2. 다 된 반죽은 랩을 씌우거나 위생팩을 덮어서 둥근 고무줄로 밀봉해 실온에 1~2시간 1차 발효합니다. 날씨에 따라 시간은 달라지고 반죽이 2배 이상 부풀때까지 해주시면 됩니다.",
			"3. 부푼 모습입니다.",
			"4. 필링은 버터만 빼고 나머지 재료를 골고루 섞어둡니다. 버터는 도우에 직접 바를거에요.",
			"5. 이제 도우를 밀어줍니다. 되도록 직사각형 모양으로 밀어준 후 솔로 버터를 골고루 발라주어요 섞어둔 필링 재료를 골고루 잘 뿌린 후 돌돌 말아주어요.",
			"6. 끝 매무새는 반죽을 꼭꼭 꼬집어서 필링이 새나오지 않게 꼼꼼히 마무리하고 일정한 간격으로 대략 10등분 해줍니다.",
			"7. 오븐팬에 종이호일 깔고 하나씩 동그랗게 모양을 잡아 놓아준 뒤 40분 정도 2차 발효를 합니다. 겉이 마르지 않게 비닐로 살짝 덮어주고요2차 발효가 지난 뒤 통통해진 모습을 볼 수 있습니다.",
			"8. 180도로 예열한 오븐에 15분~18분 정도 구워줍니다.",
			"9. 아이싱 재료를 모두 넣고 크림화해주세요. 빵이 다 구워지면 바로 아이싱을 덧발라 빵의 열기와 함께 녹고 굳어질 수 있게 합니다.",
			"10. 시나몬롤이 다 구어지면 아이싱을 신속하게 덧발라줍니다. 짤주머니로 짜주셔도 됩니다."
		]
	},
	{
		"name": "시나몬향이 어울리는 호두타르트 만들기",
		"ingredients": "버터 60g, 노른자 1개, 설탕 40g, 박력분 110g, 아몬드가루 10g, 바닐라익스트랙 1/2tsp (생략가능), 호두 150g, 계란 2개, 설탕 60g, 물엿 80g, 시나몬가루 1tsp, 녹인 버터 40g, 바닐라익스트랙 1tsp (생략가능)",
		"recipe": [
			"1. (타르트지/파트 슈크레) 볼에 말랑한 버터와 설탕을 넣고 크림을 만들다가 노른자+바닐라익스트랙을 2번 나누어 넣어가며 섞어주세요.",
			"2. 가루류를 반씩 나누어 넣어가며 섞어주세요.",
			"3. 가루가 보이지 않으면 한 덩어리로 뭉쳐주세요.",
			"4. 반죽을 비닐에 담고 냉장고에 30분 휴지시켜주세요.",
			"5. 휴지가 끝나면 반죽을 두께 0.3~0.4cm 정도로 넓게 밀어주세요.",
			"6. 반죽을 틀에 담아 모양을 잡아주고, 포크로 구멍을 내주세요. (필링)을 만들 동안 냉장고에 넣어두세요.",
			"7. [호두의 쓴맛을 줄이는 방법!] 끓는 물에 호두를 2분간 데친 후 건져서 키친타월로 물기를 제거해주세요. 그런 다음 180℃에서 5분간 구워주세요. *기름기 없는 프라이팬에 볶아도 됩니다! *이 단계는 생략해도 괜찮아요!",
			"8. 볼에 계란을 넣고 살짝 풀어주세요. 그런 다음 설탕과 물엿, 시나몬가루, 바닐라익스트랙을 넣고 골고루 섞어주세요. *백설탕 보다는 갈색설탕을 사용하시면 색이 더 예쁘게 나와요!",
			"9. 적당한 크기로 자른 호두를 고르게 담아주세요.",
			"10. 필링도 담아주세요.",
			"11. 170℃에서 35~40분 구워주세요. *구워지는 동안 가운데가 볼록하게 부푸는 데 식은면 다시 가라 앉아요! 잘 구워졌으면 식힘마에 올려 대충 식힌 후 냉장고에 넣어 완전히 차갑게 식혀주세요! *하루 동안 넣어두는 게 좋아요!"
		]
	},
	{
		"name": " 크림치즈 적신 시나몬롤의 치명적인유혹! 호떡믹스로 만드는 초간단 시나몬롤",
		"ingredients": "시판 호떡믹스 1봉지, 슈가파우더 1/2컵, 크림치즈 4큰술, 우유 3큰술",
		"recipe": [
			"1. 시판 호떡믹스의 포장지에 표기된 조리법을 참고하여 반죽을 해요. : 따뜻한 물(우유)에 이스트 섞기 -> 밀가루와 반죽하기",
			"2. 반죽을 밀대로 넓게 밀어 편 뒤 호떡믹스에 동봉된 계피설탕가루를 고루 뿌려요.",
			"3. 돌돌말고 반죽 끝을 꼬집어가며 이어 붙여요.",
			"4. 2.5cm 두께로 송송 썰어요.",
			"5. 중약 불로 달군 팬에 식용유를 두르고 반죽을 올려 노릇하게 색이 날때까지 사방을 굴려가며 구워요.",
			"6. 크림치즈아이싱을 만들어 비닐팩(또는 짤주머니)에 담아요.",
			"7. 시나몬롤에 뿌려 마무리."
		]
	},
	{
		"name": "호떡믹스로 만들어본 시나몬롤",
		"ingredients": "호떡믹스, 버터, 우유, 계란물",
		"recipe": [
			"1. 볼에 호떡믹스에 들어있는 하얀가루를 다 넣어주신 다음 버터 1큰술을 녹여 넣어주세요.",
			"2. 그리고 따뜻한 우유 180ml도 넣고 같이 들어있던 이스트도 넣어 반죽해주시면 절반은 완성 되는거랍니다.",
			"3. 반죽은 상온에서 1시간 정도 발효시켜 주세요.",
			"4. 시간이 흐른 뒤 쟁반에 반죽을 넓게 펴 바른 다음 그 위에 녹인 버터를 꼼꼼히 발라주세요.",
			"5. 그리고 호떡믹스에 있던 잼믹스를 넓게 펴 발라주기. 땅콩도 있고 있을껀 다 있네요.",
			"6. 끝에서 부터 돌돌말아주고 세모모양으로 썬 다음 젓가락이나 긴 막대라 가운데를 꼭 눌러주세요.",
			"7. 그러면 바로 이 모양이 되지요 가운데 자국은 생략해도 좋으나 모양이 이쁜게 더 좋잖아요.",
			"8. 계란물을 위에 살짝 발라주고 오븐에 구워줄꺼예요 180도로 예열된 오븐에 10분정도 구워주면 맛있는 시나몬롤 완성이요.",
			"9. 우유랑 곁들어 먹으면 완전 금상첨화."
		]
	},
	{
		"name": "초간단! 베이글 시나몬 러스크 만들기｜효썸",
		"ingredients": "베이글 1개, 무염버터 25g, 설탕 40g, 계피가루 1/2tsp",
		"recipe": [
			"1. 베이글을 반으로 자른 다음 반을 4등분으로 잘라주세요(총 8조각이 되도록).",
			"2. 설탕에 계피가루를 넣고 골고루 섞어주세요.",
			"3. 한 면에 부드러워진 버터를 발라주세요.",
			"4. 버터를 바른 면에 계피설탕을 묻혀주세요(꾹꾹 눌러 듬뿍 묻혀주세요).",
			"5. 170℃로 예열한 오븐에 10분간 구워주세요.",
			"6. 잘 구워졌으면 식힘만에 올려 충분히 식혀주세요."
		]
	}
]