[
	{
		"name": "탄탄면, 땅콩버터로 맛을 낸 면요리",
		"ingredients": "사골국물 750ml, 다진 돼지고기 90g, 숙주 80g, 칼국수면 2인분, 썰은 표고버섯 2개, 삶은 달걀 1개, 땅콩 분태 1.5T, 썰은 흰대파 2T, 부순 베트남고추 약간 (or 건홍고추), 간장 1T, 두반장 1/2T, 맛술 1T, 다진 마늘 1/2T, 다진 생강 1t, 고추기름 1T, 썰은 흰대파 1T, 땅콩버터 2T, 두반장 1.3T, 간장 1T, 굴소스 4/5T",
		"recipe": [
			"1. 먼저 고기볶음부터 만들어볼까요. 프라이팬에 고추기름, 다진 마늘 & 생강, 썰은 흰 대파 1T을 넣고 중불에서 1분 30초 볶아주세요.",
			"2. 그리고 다진 돼지고기, 두반장, 간장, 맛술을 넣고 수분기가 날아갈 때까지 (대략 5~6분) 볶아주세요.",
			"3. 완성된 볶음을 그릇에 담아, 차갑게 식혀주면 된답니다.",
			"4. 칼국수면은 삶기 전에 면을 찬물에 살짝 담갔다가 바로 빼낸 다음,",
			"5. 펄펄 끓는 물에 넣고 중불에서 4~5분 삶아주세요.",
			"6. 그리고 삶은 칼국수 면은 찬물에 살짝 헹궈주면 된답니다.",
			"7. 냄비에 사골국물, 썰은 표고버섯, 국물 소스 재료들을 넣고 중불에서 끓여주세요.",
			"8. 그리고 부글부글 끓어오르면, 삶아놓은 칼국수면을 넣고 30초만 더 끓여주세요.",
			"9. 끓여놓은 걸 그릇에 담고, 그 위로 숙주, 삶은 달걀, 땅콩 분태, 흰대파, 베트남 고추, 돼지고기볶음을 올려주면 끝."
		]
	},
	{
		"name": "(라면의 화려한 변신) 탄탄면 / 탄탄면 만들기",
		"ingredients": "라면사리 2봉지, 사골육수, 돼지고기 다짐육 100g, 청경채 3개, 숙주나물 1줌, 다진 파 1큰술 (고명), 맛술 1큰술, 후춧가루 약간, 고추기름 2큰술, 다진 마늘 1큰술, 다진 파 2큰술, 진간장 1큰술, 두반장 2큰술, 땅콩버터 2큰술",
		"recipe": [
			"1. #탄탄면#라면요리#탄탄면만들기#라면추천#라면요리",
			"2. · 다진 돼지고기는 키친타월로 꾹꾹 눌러 핏물을 빼주고",
			"3. 맛술 1 큰 술, 후춧가루 약간 넣고 밑간을 해줍니다",
			"4. 청경채는 하나씩 떼서 씻은 후  큰 잎들은 세로로 한 번 잘라줬습니다",
			"5. · 청경채와 숙주 깨끗이 씻어서 준비",
			"6. · 소금 0.5 큰 술 넣고 끓는 물에",
			"7. 청경채 살짝 데쳐주고",
			"8. 숙주나물을 데쳐줍니다",
			"9. - 끓는 물에 약 15~20초 ( 고명으로 올려 아삭한 식감을 살리기 위해 살짝 데쳐줬는데 아삭한 식감이 싫으신 분들은 더 오래 삶아주세요 )",
			"10. · 고추기름 2 큰 술, 다진 마늘 1 큰 술, 다진 파 2 큰 술",
			"11. 센 불에 약 30초간 먼저 볶아줍니다",
			"12. · 밑간해 놓은 다진 돼지고기도 넣고 뭉치지 않게   뒤집개를 세워 으깨가면서 볶습니다",
			"13. · 두반장 2 큰 술, 진간장 1 큰 술을",
			"14. 팬 가장자리에 고기랑 분리해서 약 10초간 놔뒀다가 (불향 입히기) 돼지고기와 섞어서 볶아줍니다",
			"15. · 볶다가 시판용 사골육수 + 물 3컵 (종이컵 기준) 넣어주고 땅콩버터 2 큰 술 넣어서 팔팔 끓여주면",
			"16. 탄탄면 국물은 완성!!!",
			"17. 라면 사리는 삶아서 체에 밭쳐 물기를 빼줍니다",
			"18. · 라면사리 담고 데쳐놓은 청경채와 숙주나물, 다진 파를 올린 뒤",
			"19. 국물을 부어주면 탄탄면 완성!!!",
			"20. 고기 듬뿍 고소하고 진한 맛의 탄탄면"
		]
	},
	{
		"name": "땅콩버터가 들어가 고소한 탄탄면 만들기",
		"ingredients": "중면 160g, 청경채 6개 (고명용), 시판용 사골육수 600g, 땅콩버터 1큰술, 간장 1큰술, 두반장 1/2큰술, 다진마늘 1/2큰술, 돼지고기 다짐육 100g, 고춧가루 1큰술, 기름 2큰술, 다진마늘 1/2큰술, 다진파 1큰술, 간장 1큰술, 두반장 1/2큰술, 설탕 1/2큰술, 조미술 1큰술",
		"recipe": [
			"1. -끓는 물에 소금 넣어 청경채 데치기",
			"2. 청경채는 머리부분이 두꺼워서 머리부분부터 15초 정도 담근 후 전체적으로 담갔다 빼주세요.  -데친 청경채 찬물에 헹구기, 손으로 물기 짜기",
			"3. -기름에 고춧가루 넣어 약한 불에서 볶아 즉석 고추기름 만들기",
			"4. -돼지고기 다짐육 외 고명 재료 모두 넣어 볶아주기",
			"5. -사골육수 외 재료 준비하기  -데친 청경채, 돼지고기 고명 준비 끝~!",
			"6. -사골육수 끓으면 준비한 국물재료 넣어 한소끔 끓이기",
			"7. 보글보글 끓으면 국물 준비 끝~!",
			"8. -중면 삶기, 찬물에 헹구기, 다시 따뜻한 물로 면 데우기  -면 삶을 때 끓어오를 때 찬물을 부어줘야 면이 쫄깃해져요.",
			"9. -그릇에 면, 국물, 청경채, 돼지고기 고명 올려주면 탄탄면 완성~!!"
		]
	},
	{
		"name": "집에서 만들어먹는 백종원표 탄탄면",
		"ingredients": "라면 1봉지, 물 3cup, 땅콩버터 1T, 대파 10cm, 고춧가루 1T",
		"recipe": [
			"1. 대파는 송송썰어 준비한다.",
			"2. 냄비에 물을 넣고 면과 라면 후레이크를 넣고 끓인다.",
			"3. 면이 익으면 물을 반 정도 남기고 버린다.",
			"4. 라면 수프, 땅콩버터, 대파, 고춧가루를 넣고 잘 섞어 완성한다."
		]
	},
	{
		"name": "탄탄면",
		"ingredients": "생면 200 g, 돈사골육수 600ml , 땅콩버터 1 큰술, 두반장 1/2 큰술, 간장 1/2 큰술, 자연재료산들애국내산한우 1/2 큰술, 다진파 1/2 큰술, 다진마늘 1/2 큰술, 캐슈넛 1 큰술, 땅콩 1 큰술, 짜사이 1 큰술, 다진돼지고기 2 큰술, 간장 1 큰술, 두반장 1/2 큰술, 고추기름 2 큰술, 다진파 1/2 큰술, 다진마늘 1/2 큰술",
		"recipe": [
			"1. 땅콩과캐슈넛은 칼로 다진다. 청경채는 세로로 자른 후 살짝 데친다. 고추기름 두른 팬에 다진 파, 마늘, 다진 돼지고기를 볶다가 맛간장, 두분장을 넣고 볶아준다.",
			"2. 냄비에 소량의 돈사골육수를 붓고 땅콩버터, 다진 파, 다진 마늘, 두반장, 간장을 넣고 끓이다가 돈사골육수를 마저 붓고 끓여 육수를 만든다.",
			"3. 다른 냄비에 물을 넣고 끓어 오르면 생면을 넣어 삶는다. TIP) 거품이 넘칠 때 찬물을 넣어 면에 찰기를 더한다. 삶은 후에는 찬물 샤워를 해주면 찰기있는 면을 만들 수 있다.",
			"4. 그릇에 면을 담고 육수부은 뒤 청경채, 짜사이, 볶은 돼지고기, 땅콩과 캐슈넛을 올려 완성한다."
		]
	}
]